{
    "validations": {
        "constraint": [
            {
                "fieldName": "label",
                "validators": [
                    {
                        "key": "required"
                    }
                ]
            },
            {
                "fieldName": "name",
                "validators": [
                    {
                        "key": "required"
                    }
                ]
            },
            {
                "fieldName": "description",
                "validators": [
                    {
                        "key": "regex",
                        "validator": {
                            "type": "extendedAlphanumericRegex"
                        }
                    }
                ]
            },
            {
                "fieldName": "valueTypeCd",
                "validators": [
                    {
                        "key": "required"
                    }
                ]
            },
            {
                "fieldName": "secondValue",
                "validators": [
                    {
                        "key": "range_check",
                        "validator": {
                            "type": "range-check"
                        }
                    }
                ]
            }
        ]
    }
}
