{
    "searchSettingsTypes": [
        {
            "label": "common.static",
            "value": "static"
        },
        {
            "label": "common.driver",
            "value": "driver"
        }
    ],
    "settings": {
        "Configuration": [
            {
                "title": "dashboard.widgetEditor.discoveryWidget.facets.title",
                "type": "FacetsSettings"
            },
            {
                "title": "dashboard.widgetEditor.discoveryWidget.search.title",
                "type": "SearchSettings"
            },
            {
                "title": "dashboard.widgetEditor.export.title",
                "type": "Export"
            },
            {
                "title": "dashboard.widgetEditor.customMessages.title",
                "type": "CustomMessages"
            }
        ],
        "Interactions": [
            {
                "title": "dashboard.widgetEditor.interactions.crossNavigation",
                "type": "CrossNavigation"
            },
            {
                "title": "dashboard.widgetEditor.interactions.link",
                "type": "Link"
            },
            {
                "title": "dashboard.widgetEditor.interactions.preview",
                "type": "Preview"
            }
        ],
        "Responsive": [
            {
                "title": "dashboard.widgetEditor.responsive.title",
                "type": "Responsive"
            }
        ],
        "Style": [
            {
                "title": "dashboard.widgetEditor.titles.title",
                "type": "Title"
            },
            {
                "title": "dashboard.widgetEditor.headers.title",
                "type": "Headers"
            },
            {
                "title": "common.columns",
                "type": "ColumnStyle"
            },
            {
                "title": "dashboard.widgetEditor.rows.title",
                "type": "RowsStyle"
            },
            {
                "title": "dashboard.widgetEditor.background",
                "type": "BackgroundColorStyle"
            },
            {
                "title": "dashboard.widgetEditor.borders.title",
                "type": "BordersStyle"
            },
            {
                "title": "dashboard.widgetEditor.padding.title",
                "type": "PaddingStyle"
            },
            {
                "title": "dashboard.widgetEditor.shadows.title",
                "type": "ShadowsStyle"
            }
        ],
        "Tooltips": [
            {
                "title": "dashboard.widgetEditor.tooltips.title",
                "type": "Tooltips"
            }
        ]
    },
    "settingsListOptions": [
        {
            "icon": "fa fa-cogs",
            "label": "dashboard.widgetEditor.configuration",
            "value": "Configuration"
        },
        {
            "icon": "fa fa-paint-brush",
            "label": "common.style",
            "value": "Style"
        },
        {
            "icon": "fa fa-hand-pointer",
            "label": "dashboard.widgetEditor.interactions.title",
            "value": "Interactions"
        },
        {
            "icon": "fa fa-commenting",
            "label": "dashboard.widgetEditor.tooltips.title",
            "value": "Tooltips"
        },
        {
            "icon": "pi pi-tablet",
            "label": "dashboard.widgetEditor.responsive.title",
            "value": "Responsive"
        }
    ]
}
