{
    "style": {
        "columnStyle": {
            "height": "25px"
        },
        "maxWidth": {
            "width": "100%"
        }
    },
    "validations": {
        "dataset": [
            {
                "fieldName": "flatTableName",
                "validators": [
                    {
                        "key": "required",
                        "validator": {
                            "type": "flat-fields-required"
                        }
                    }
                ]
            },
            {
                "fieldName": "dataSourceFlat",
                "validators": [
                    {
                        "key": "required",
                        "validator": {
                            "type": "flat-fields-required"
                        }
                    }
                ]
            }
        ]
    }
}
