{
    "pythonResponse": "[{\"name\": \"tornado\", \"version\": \"6.0.3\"}, {\"name\": \"PyYAML\", \"version\": \"5.3\"}, {\"name\": \"Pillow\", \"version\": \"8.1.0\"}, {\"name\": \"MarkupSafe\", \"version\": \"1.1.1\"}, {\"name\": \"greenlet\", \"version\": \"0.4.15\"}, {\"name\": \"gevent\", \"version\": \"20.4.0\"}, {\"name\": \"cryptography\", \"version\": \"2.8\"}, {\"name\": \"cffi\", \"version\": \"1.14.0\"}, {\"name\": \"wheel\", \"version\": \"0.34.2\"}, {\"name\": \"Werkzeug\", \"version\": \"1.0.0\"}, {\"name\": \"urllib3\", \"version\": \"1.25.8\"}, {\"name\": \"typing-extensions\", \"version\": \"3.7.4.3\"}, {\"name\": \"requests\", \"version\": \"2.23.0\"}, {\"name\": \"request\", \"version\": \"2019.4.13\"}, {\"name\": \"query-string\", \"version\": \"2019.4.13\"}, {\"name\": \"PyJWT\", \"version\": \"1.7.1\"}, {\"name\": \"pycparser\", \"version\": \"2.19\"}, {\"name\": \"public\", \"version\": \"2019.4.13\"}, {\"name\": \"post\", \"version\": \"2019.4.13\"}, {\"name\": \"pip\", \"version\": \"20.3.3\"}, {\"name\": \"packaging\", \"version\": \"20.1\"}, {\"name\": \"monotonic\", \"version\": \"1.5\"}, {\"name\": \"Jinja2\", \"version\": \"2.11.1\"}, {\"name\": \"itsdangerous\", \"version\": \"1.1.0\"}, {\"name\": \"idna\", \"version\": \"2.9\"}, {\"name\": \"gunicorn\", \"version\": \"20.0.4\"}, {\"name\": \"get\", \"version\": \"2019.4.13\"}, {\"name\": \"Flask\", \"version\": \"1.1.1\"}, {\"name\": \"Flask-Cors\", \"version\": \"3.0.8\"}, {\"name\": \"eventlet\", \"version\": \"0.25.2\"}, {\"name\": \"dnspython\", \"version\": \"1.16.0\"}, {\"name\": \"Click\", \"version\": \"7.0\"}, {\"name\": \"chardet\", \"version\": \"3.0.4\"}, {\"name\": \"certifi\", \"version\": \"2019.11.28\"}, {\"name\": \"bokeh\", \"version\": \"2.2.3\"}, {\"name\": \"scipy\", \"version\": \"1.2.1\"}, {\"name\": \"pandas\", \"version\": \"0.24.1\"}, {\"name\": \"numpy\", \"version\": \"1.16.1\"}, {\"name\": \"matplotlib\", \"version\": \"3.0.2\"}, {\"name\": \"kiwisolver\", \"version\": \"1.0.1\"}, {\"name\": \"six\", \"version\": \"1.12.0\"}, {\"name\": \"setuptools\", \"version\": \"39.2.0\"}, {\"name\": \"pytz\", \"version\": \"2018.9\"}, {\"name\": \"python-dateutil\", \"version\": \"2.8.0\"}, {\"name\": \"pyparsing\", \"version\": \"2.3.1\"}, {\"name\": \"cycler\", \"version\": \"0.10.0\"}]",
    "rResponse": "[[\"base\",\"3.5.1\"],[\"boot\",\"1.3-20\"],[\"class\",\"7.3-14\"],[\"cluster\",\"2.0.7-1\"],[\"codetools\",\"0.2-15\"],[\"compiler\",\"3.5.1\"],[\"datasets\",\"3.5.1\"],[\"foreign\",\"0.8-70\"],[\"graphics\",\"3.5.1\"],[\"grDevices\",\"3.5.1\"],[\"grid\",\"3.5.1\"],[\"KernSmooth\",\"2.23-15\"],[\"lattice\",\"0.20-35\"],[\"MASS\",\"7.3-50\"],[\"Matrix\",\"1.2-14\"],[\"methods\",\"3.5.1\"],[\"mgcv\",\"1.8-24\"],[\"nlme\",\"3.1-137\"],[\"nnet\",\"7.3-12\"],[\"parallel\",\"3.5.1\"],[\"rpart\",\"4.1-13\"],[\"spatial\",\"7.3-11\"],[\"splines\",\"3.5.1\"],[\"stats\",\"3.5.1\"],[\"stats4\",\"3.5.1\"],[\"survival\",\"2.42-3\"],[\"tcltk\",\"3.5.1\"],[\"tools\",\"3.5.1\"],[\"utils\",\"3.5.1\"]]",
    "validations": {
        "dataset": [
            {
                "fieldName": "pythonEnvironment",
                "validators": [
                    {
                        "key": "required",
                        "validator": {
                            "type": "python-fields-required"
                        }
                    }
                ]
            },
            {
                "fieldName": "dataframeName",
                "validators": [
                    {
                        "key": "required",
                        "validator": {
                            "type": "python-fields-required"
                        }
                    }
                ]
            }
        ]
    }
}
