{
    "validations": {
        "configuration": [
            {
                "fieldName": "label",
                "validators": [
                    {
                        "key": "required"
                    },
                    {
                        "key": "maximumCharacters",
                        "validator": {
                            "params": {
                                "max": 100
                            },
                            "type": "maxLength"
                        }
                    },
                    {
                        "key": "regex",
                        "validator": {
                            "type": "extendedAlphanumericRegex"
                        }
                    }
                ]
            },
            {
                "fieldName": "name",
                "validators": [
                    {
                        "key": "required"
                    },
                    {
                        "key": "maximumCharacters",
                        "validator": {
                            "params": {
                                "max": 100
                            },
                            "type": "maxLength"
                        }
                    },
                    {
                        "key": "regex",
                        "validator": {
                            "type": "extendedAlphanumericRegex"
                        }
                    }
                ]
            },
            {
                "fieldName": "description",
                "validators": [
                    {
                        "key": "maximumCharacters",
                        "validator": {
                            "params": {
                                "max": 500
                            },
                            "type": "maxLength"
                        }
                    },
                    {
                        "key": "regex",
                        "validator": {
                            "type": "extendedAlphanumericRegex"
                        }
                    }
                ]
            },
            {
                "fieldName": "active",
                "validators": []
            },
            {
                "fieldName": "valueCheck",
                "validators": []
            },
            {
                "fieldName": "category",
                "validators": [
                    {
                        "key": "required"
                    }
                ]
            }
        ]
    }
}
